pykitsu/__init__.py
pykitsu/client.py
pykitsu/exceptions.py
pykitsu/value_errors.py
pykitsu/core/get_trending.py
pykitsu/core/random.py
pykitsu/core/search.py
pykitsu/core/search_by_id.py
pykitsu/utils/__init__.py
pykitsu/utils/helpers.py
pykitsu/utils/tools.py
pykitsu-0.3.9.dist-info/LICENCE
pykitsu-0.3.9.dist-info/METADATA
pykitsu-0.3.9.dist-info/WHEEL
pykitsu-0.3.9.dist-info/top_level.txt
pykitsu-0.3.9.dist-info/RECORD
