Metadata-Version: 2.1
Name: pykitsu
Version: 0.3.9
Summary: A fast and asynchronous API wrapper for kitsu.io
Home-page: https://github.com/ore0Os/pykitsu
Author: ore0Os
Project-URL: Bug Tracker, https://github.com/ore0Os/pykitsu/issues
Classifier: Programming Language :: Python :: 3
Classifier: License :: OSI Approved :: MIT License
Classifier: Operating System :: OS Independent
Requires-Python: >=3.7
License-File: LICENCE
Requires-Dist: aiohttp
Requires-Dist: colorama
